<?xml version="1.0" encoding="UTF-8"?>
<!DOCTYPE properties SYSTEM "http://java.sun.com/dtd/properties.dtd">
<properties>
<comment>auxiliary in Croatian. File generated from metadata database version 1.1.0 created on the 2022-09-14T16:05:55</comment>
<entry key="auxiliary|text|accessibility">Kriteriji dostupnosti</entry>
<entry key="auxiliary|text|additional-role">Dodatne uloge</entry>
<entry key="auxiliary|text|adhoc-communication">Ad hoc komunikacijski kanal</entry>
<entry key="auxiliary|text|award-criteria">Kriteriji za dodjelu</entry>
<entry key="auxiliary|text|beneficial-owner">Stvarni vlasnik</entry>
<entry key="auxiliary|text|buyer">Kupac</entry>
<entry key="auxiliary|text|change">Promjena</entry>
<entry key="auxiliary|text|concession-value">Koncesije</entry>
<entry key="auxiliary|text|contract-information">Informacije o ugovoru o kupnji</entry>
<entry key="auxiliary|text|contract-terms">Uvjeti ugovora</entry>
<entry key="auxiliary|text|contractor-legal-form">Pravni oblik izvoditelja</entry>
<entry key="auxiliary|text|criterion">Kriterij</entry>
<entry key="auxiliary|text|cross-border-law">Primjenjivo prekogranično pravo</entry>
<entry key="auxiliary|text|design-contest-terms">Uvjeti režima natječaja</entry>
<entry key="auxiliary|text|direct-award">Izravno sklapanje</entry>
<entry key="auxiliary|text|duration">Trajanje</entry>
<entry key="auxiliary|text|dynamic-purchasing-system">Informacije o dinamičkom sustavu nabave</entry>
<entry key="auxiliary|text|electronic-auction">Elektronička dražba</entry>
<entry key="auxiliary|text|estimated-duration">Procijenjeno trajanje</entry>
<entry key="auxiliary|text|eu-funds-used">Informacije o sredstvima Europske unije upotrijebljenima za financiranje ugovora</entry>
<entry key="auxiliary|text|exclusion-grounds">Razlozi za isključenje</entry>
<entry key="auxiliary|text|framework-agreement">Okvirni sporazum</entry>
<entry key="auxiliary|text|general-information">Opće informacije</entry>
<entry key="auxiliary|text|group-framework-value">Procijenjena vrijednost okvirnih sporazuma u skupini grupa</entry>
<entry key="auxiliary|text|group-of-lots">Skupina grupa</entry>
<entry key="auxiliary|text|information-employment">Informacije o radnom zakonodavstvu dostupne su na</entry>
<entry key="auxiliary|text|information-fiscal">Informacije o fiskalnom zakonodavstvu dostupne su na</entry>
<entry key="auxiliary|text|late-tenderer-info">Informacije koje se mogu dopuniti nakon roka za podnošenje</entry>
<entry key="auxiliary|text|legal-basis">Pravna osnova</entry>
<entry key="auxiliary|text|lot">Serija</entry>
<entry key="auxiliary|text|modification">Izmjena</entry>
<entry key="auxiliary|text|non-winning-tender">Ponuditelji koji nisu odabrani</entry>
<entry key="auxiliary|text|notice-information">Obavijest</entry>
<entry key="auxiliary|text|options">Opcije</entry>
<entry key="auxiliary|text|organisation-cpb-acquiring">Središnje tijelo za nabavu koje nabavlja robu i/ili usluge namijenjene drugim kupcima</entry>
<entry key="auxiliary|text|organisation-cpb-awarding">Središnje tijelo za nabavu koje dodjeljuje javne ugovore ili sklapa okvirne sporazume za radove, robu ili usluge namijenjene drugim kupcima</entry>
<entry key="auxiliary|text|organisation-esender">ePošiljatelj</entry>
<entry key="auxiliary|text|organisation-financing">Organizacija iz čijih se proračunskih sredstava plaća ugovor</entry>
<entry key="auxiliary|text|organisation-group-leader">Voditelj skupine</entry>
<entry key="auxiliary|text|organisation-mediation">Organizacija za postupke mirenja</entry>
<entry key="auxiliary|text|organisation-paying">Organizacija koja izvršava plaćanje</entry>
<entry key="auxiliary|text|organisation-processing-tenders">Organizacija koja obrađuje ponude/zahtjeve za sudjelovanje</entry>
<entry key="auxiliary|text|organisation-providing-docs">Organizacija koja osigurava izvanmrežni pristup dokumentaciji o nabavi</entry>
<entry key="auxiliary|text|organisation-providing-info-employment">Pružatelj informacija o radnom zakonodavstvu</entry>
<entry key="auxiliary|text|organisation-providing-info-environment">Pružatelj informacija iz zakonodavstva o okolišu</entry>
<entry key="auxiliary|text|organisation-providing-info-procedure">Organizacija koja pruža dodatne informacije o postupku javne nabave</entry>
<entry key="auxiliary|text|organisation-providing-info-review">Organizacija koja pruža informacije o žalbenom postupku</entry>
<entry key="auxiliary|text|organisation-providing-info-taxes">Organizacija koja pruža informacije o općem regulatornom okviru za poreze koji se primjenjuje u mjestu izvršenja ugovora</entry>
<entry key="auxiliary|text|organisation-providing-procurement-service">Pružatelj usluga javne nabave</entry>
<entry key="auxiliary|text|organisation-review">Organizacija za preispitivanje (pravnu zaštitu)</entry>
<entry key="auxiliary|text|organisation-review-timelimit">Organizacija koja pruža informacije o rokovima za postupke pravne zaštite</entry>
<entry key="auxiliary|text|organisation-signing-contract">Organizacija koja potpisuje ugovor</entry>
<entry key="auxiliary|text|organisation-tender-evaluation">Organizacija koja ocjenjuje ponude</entry>
<entry key="auxiliary|text|organisation-tender-recipient">Organizacija koja prima zahtjeve za sudjelovanje/ponudama</entry>
<entry key="auxiliary|text|organisations">Organizacije</entry>
<entry key="auxiliary|text|other-contact-point">Druge kontaktne točke</entry>
<entry key="auxiliary|text|part">Dio</entry>
<entry key="auxiliary|text|place-performance">Mjesto izvršavanja</entry>
<entry key="auxiliary|text|previous-planning">Prethodno planiranje</entry>
<entry key="auxiliary|text|procedure">Postupak</entry>
<entry key="auxiliary|text|procedure-terms">Uvjeti postupka</entry>
<entry key="auxiliary|text|procurement-documents">Dokumentacija o nabavi</entry>
<entry key="auxiliary|text|procurement-terms">Uvjeti javne nabave</entry>
<entry key="auxiliary|text|public-opening">Informacije o javnom otvaranju</entry>
<entry key="auxiliary|text|publication-information">Podatci o objavi</entry>
<entry key="auxiliary|text|purpose">Svrha</entry>
<entry key="auxiliary|text|range-tenders">Raspon ponuda</entry>
<entry key="auxiliary|text|received-submissions">Zaprimljene ponude ili zahtjevi za sudjelovanje</entry>
<entry key="auxiliary|text|renewal">Produljenje</entry>
<entry key="auxiliary|text|results">Rezultati</entry>
<entry key="auxiliary|text|results-procurement-procedure">Rezultat postupka nabave</entry>
<entry key="auxiliary|text|review-requests-irregularity-type">Vrsta navodne nepravilnosti</entry>
<entry key="auxiliary|text|review-requests-summary">Sažetak zahtjeva za pravnu zaštitu koje je kupac zaprimio</entry>
<entry key="auxiliary|text|second-stage">Informacije o drugoj fazi postupka u dvije faze</entry>
<entry key="auxiliary|text|selection-criteria">Kriteriji odabira</entry>
<entry key="auxiliary|text|statistical-information">Statističke informacije</entry>
<entry key="auxiliary|text|statistics-strategic">Statistički podaci o strateškoj nabavi</entry>
<entry key="auxiliary|text|strategic-procurement">Strateška javna nabava</entry>
<entry key="auxiliary|text|subcontracting-terms">Podugovaranje</entry>
<entry key="auxiliary|text|submission-terms">Uvjeti podnošenja</entry>
<entry key="auxiliary|text|techniques">Tehnike</entry>
<entry key="auxiliary|text|tender">Natječaj</entry>
<entry key="auxiliary|text|touchpoint">Posebna kontaktna točka</entry>
<entry key="auxiliary|text|value">Vrijednost</entry>
<entry key="auxiliary|text|winner">Pobjedničke ponude</entry>
<entry key="auxiliary|text|winner-info">Informacije o pobjednicima</entry>
<entry key="auxiliary|text|winner-subcontractor">Podizvođači pobjednika</entry>
</properties>
