<?xml version="1.0" encoding="UTF-8"?>
<!DOCTYPE properties SYSTEM "http://java.sun.com/dtd/properties.dtd">
<properties>
<comment>group in Bulgarian. File generated from metadata database version 1.5.0 created on the 2022-12-14T11:00</comment>
<entry key="group|name|GR-Business-Address">Адрес</entry>
<entry key="group|name|GR-Business-Contact">Свържете се</entry>
<entry key="group|name|GR-Business-Party">Стопански субект</entry>
<entry key="group|name|GR-Business-Publication">Обявяване</entry>
<entry key="group|name|GR-Business-Section">Известие</entry>
<entry key="group|name|GR-Buyer">Информация за договарящата страна и доставчика</entry>
<entry key="group|name|GR-Change">Промяна</entry>
<entry key="group|name|GR-Company">Организация</entry>
<entry key="group|name|GR-Company-Address">Адрес</entry>
<entry key="group|name|GR-Company-BuyerExclusive">Информация, свързана изключително с купувача</entry>
<entry key="group|name|GR-Company-Contact">Звено за контакт</entry>
<entry key="group|name|GR-Company-EconomicOperatorExclusive">Информация, свързана изключително с икономическия оператор</entry>
<entry key="group|name|GR-Content">Съдържание</entry>
<entry key="group|name|GR-ContractingAuthority">Възлагащ орган</entry>
<entry key="group|name|GR-ContractingAuthority-Buyer">Купувач</entry>
<entry key="group|name|GR-Lot-AddInfo">Организация, предоставяща допълнителна информация</entry>
<entry key="group|name|GR-Lot-AdditionalInformation">Допълнителна информация</entry>
<entry key="group|name|GR-Lot-AuctionTerms">Условия на търга</entry>
<entry key="group|name|GR-Lot-AwardingConsequences">Последици от присъждането</entry>
<entry key="group|name|GR-Lot-Candidates">Кандидати</entry>
<entry key="group|name|GR-Lot-ContractExecutionRequirements">Изисквания за изпълнение на договора</entry>
<entry key="group|name|GR-Lot-ContractExtension">Подновяване на договора</entry>
<entry key="group|name|GR-Lot-ContractingSystem">Система на договаряне</entry>
<entry key="group|name|GR-Lot-Deadline">Срокове за преразглеждане</entry>
<entry key="group|name|GR-Lot-Deadlines1">Крайни срокове I</entry>
<entry key="group|name|GR-Lot-Deadlines2">Крайни срокове II</entry>
<entry key="group|name|GR-Lot-Description">Description of the lot Описание на партидата</entry>
<entry key="group|name|GR-Lot-DocProvider">Организация, предоставяща документи</entry>
<entry key="group|name|GR-Lot-EUFunds">Използване на фондовете на ЕС</entry>
<entry key="group|name|GR-Lot-EconomicOperatorShortlist">Участници, които вече са избрани</entry>
<entry key="group|name|GR-Lot-ElectronicCatalog">Електронен каталог</entry>
<entry key="group|name|GR-Lot-ElectronicSignatureRequired">Електронен подпис</entry>
<entry key="group|name|GR-Lot-EmployLegis">Информация за трудовото законодателство</entry>
<entry key="group|name|GR-Lot-EnvironLegis">Информация за законодателството в областта на околната среда</entry>
<entry key="group|name|GR-Lot-FinancialGuarantee">Финансова гаранция</entry>
<entry key="group|name|GR-Lot-FinancialTerms">Финансово споразумение</entry>
<entry key="group|name|GR-Lot-FiscalLegis">Информация за фискалното законодателство</entry>
<entry key="group|name|GR-Lot-FrameworkAgreement">Информация относно рамковото споразумение</entry>
<entry key="group|name|GR-Lot-GpaAgreement">Споразумение за държавните поръчки (СДП)</entry>
<entry key="group|name|GR-Lot-Mediator">Организация за медиация</entry>
<entry key="group|name|GR-Lot-PlannedDuration">Планирана продължителност</entry>
<entry key="group|name|GR-Lot-PlannedDuration-Dates">Продължителност</entry>
<entry key="group|name|GR-Lot-PlannedDuration-Period">Период</entry>
<entry key="group|name|GR-Lot-PostAwardProcess">Процес след възлагането на поръчката</entry>
<entry key="group|name|GR-Lot-Procedure">Възлагане на поръчката</entry>
<entry key="group|name|GR-Lot-ProcurementDocuments">Тръжна документация</entry>
<entry key="group|name|GR-Lot-ProcurementType">Вид обществена поръчка</entry>
<entry key="group|name|GR-Lot-ProcurementType-Accessibility">Критерии за достъпност</entry>
<entry key="group|name|GR-Lot-ProcurementType-Strategic">Стратегически поръчки</entry>
<entry key="group|name|GR-Lot-PublicOpeningEvent">Информация за публичното отваряне</entry>
<entry key="group|name|GR-Lot-Purpose">Цел;</entry>
<entry key="group|name|GR-Lot-QualityTarget">Цели по отношение на качеството</entry>
<entry key="group|name|GR-Lot-Requirements2SecurityClearance1">Изисквания</entry>
<entry key="group|name|GR-Lot-Review">Преразглеждане</entry>
<entry key="group|name|GR-Lot-ReviewInfo">Организация, предоставяща информация за прегледа</entry>
<entry key="group|name|GR-Lot-ReviewOrg">Организация за преглед</entry>
<entry key="group|name|GR-Lot-Scope">Обхват на поръчката</entry>
<entry key="group|name|GR-Lot-Scope-MainClassification">Класиране</entry>
<entry key="group|name|GR-Lot-SecurityClearance2">Разрешение за достъп</entry>
<entry key="group|name|GR-Lot-SelectionCriteria-SecondStageInvite">Критерии за подбор за достъп до следващия етап</entry>
<entry key="group|name|GR-Lot-SubcontractRequest">Искане за възлагане на подизпълнители</entry>
<entry key="group|name|GR-Lot-SubcontractTerms">Условия за възлагане на подизпълнители</entry>
<entry key="group|name|GR-Lot-Submission Language">Език на подаване</entry>
<entry key="group|name|GR-Lot-SubmissionInfo">Информация за подаването</entry>
<entry key="group|name|GR-Lot-SubmissionMethod">Метод на подаване</entry>
<entry key="group|name|GR-Lot-SubmissionTool">Ad hoc канал за комуникация</entry>
<entry key="group|name|GR-Lot-TenderEval">Организация, която обработва офертите</entry>
<entry key="group|name|GR-Lot-TenderReceipt">Организация, която получава офертите</entry>
<entry key="group|name|GR-Lot-TenderValidity">Валидност на офертата</entry>
<entry key="group|name|GR-Lot-TendererQualification">Информация за закъсняло подаване</entry>
<entry key="group|name|GR-Lot-TenderingTerms">Тръжни условия</entry>
<entry key="group|name|GR-Lot-Variants">Варианти</entry>
<entry key="group|name|GR-LotResult-1">Резултат 1</entry>
<entry key="group|name|GR-LotResult-2">Резултат 2</entry>
<entry key="group|name|GR-LotResult-Parties">Страни</entry>
<entry key="group|name|GR-LotResult-Section">Резултати от обособените позиции</entry>
<entry key="group|name|GR-LotResult-TenderValue">Стойност на офертата</entry>
<entry key="group|name|GR-LotTender-1">Оферта 1</entry>
<entry key="group|name|GR-LotTender-2">Оферта 2</entry>
<entry key="group|name|GR-LotTender-3">Оферта 3</entry>
<entry key="group|name|GR-LotTender-Section">Търгове</entry>
<entry key="group|name|GR-LotTender-Subcontracting">Наемане на подизпълнители</entry>
<entry key="group|name|GR-LotsGroup-AdditionalInformation">Допълнителна информация</entry>
<entry key="group|name|GR-LotsGroup-AwardCriteria-Criterion-Parameter">Award criterion</entry>
<entry key="group|name|GR-LotsGroup-AwardCriteria-Criterion-Parameters">Award criteria</entry>
<entry key="group|name|GR-LotsGroup-Description">Описание на групата партиди</entry>
<entry key="group|name|GR-LotsGroup-FrameworkAgreement">Информация относно рамковото споразумение</entry>
<entry key="group|name|GR-LotsGroup-LotDistribution">Обособени позиции, включени в групата обособени позиции</entry>
<entry key="group|name|GR-LotsGroup-Purpose">Цел;</entry>
<entry key="group|name|GR-LotsGroup-Scope">Обхват на поръчката</entry>
<entry key="group|name|GR-LotsGroup-TenderingTerms">Тръжни условия</entry>
<entry key="group|name|GR-Metadata">Метаданни</entry>
<entry key="group|name|GR-Modification">Модификация Изтегляне</entry>
<entry key="group|name|GR-NoticeResult-Section">Резултат</entry>
<entry key="group|name|GR-Organisations-Section">С нестопанска цел</entry>
<entry key="group|name|GR-Organisations-Subsection">С нестопанска цел</entry>
<entry key="group|name|GR-Part-AddInfo">Организация, предоставяща допълнителна информация</entry>
<entry key="group|name|GR-Part-AdditionalInformation">Допълнителна информация</entry>
<entry key="group|name|GR-Part-ContractExecutionRequirements">Изисквания за изпълнение на договора</entry>
<entry key="group|name|GR-Part-ContractingSystem">Система на договаряне</entry>
<entry key="group|name|GR-Part-Deadlines">Срокове</entry>
<entry key="group|name|GR-Part-Description">Описание на частта</entry>
<entry key="group|name|GR-Part-DocProvider">Организация, предоставяща документи</entry>
<entry key="group|name|GR-Part-EmployLegis">Информация за трудовото законодателство</entry>
<entry key="group|name|GR-Part-EnvironLegis">Информация за законодателството в областта на околната среда</entry>
<entry key="group|name|GR-Part-FiscalLegis">Информация за фискалното законодателство</entry>
<entry key="group|name|GR-Part-GpaAgreement">Споразумение за държавните поръчки (СДП)</entry>
<entry key="group|name|GR-Part-Mediator">Организация за медиация</entry>
<entry key="group|name|GR-Part-PlannedDuration">Планирана продължителност</entry>
<entry key="group|name|GR-Part-PlannedDuration-Dates">Продължителност</entry>
<entry key="group|name|GR-Part-PlannedDuration-Period">Период</entry>
<entry key="group|name|GR-Part-ProcurementDocuments">Тръжна документация</entry>
<entry key="group|name|GR-Part-Purpose">Цел;</entry>
<entry key="group|name|GR-Part-Review">Преразглеждане</entry>
<entry key="group|name|GR-Part-ReviewInfo">Организация, предоставяща информация за прегледа</entry>
<entry key="group|name|GR-Part-ReviewOrg">Организация за преглед</entry>
<entry key="group|name|GR-Part-Scope">Обхват на поръчката</entry>
<entry key="group|name|GR-Part-Scope-MainClassification">Класиране</entry>
<entry key="group|name|GR-Part-SubmissionInfo">Информация за подаването</entry>
<entry key="group|name|GR-Part-SubmissionTool">Ad hoc канал за комуникация</entry>
<entry key="group|name|GR-Part-TenderEval">Организация, която обработва офертите</entry>
<entry key="group|name|GR-Part-TenderReceipt">Организация, която получава офертите</entry>
<entry key="group|name|GR-Part-TendererQualification">Информация за закъсняло подаване</entry>
<entry key="group|name|GR-Part-TenderingTerms">Тръжни условия</entry>
<entry key="group|name|GR-Previous-Notice">Предишно обявление</entry>
<entry key="group|name|GR-Procedure">Възлагане на поръчката</entry>
<entry key="group|name|GR-Procedure-AdditionalInformation">Допълнителна информация</entry>
<entry key="group|name|GR-Procedure-CrossBorderLaw">Трансгранично право</entry>
<entry key="group|name|GR-Procedure-Description">Описание</entry>
<entry key="group|name|GR-Procedure-DirectAward">Пряко възлагане</entry>
<entry key="group|name|GR-Procedure-LocalCrossBorderLaw">Позоваване на местното право</entry>
<entry key="group|name|GR-Procedure-LocalLegalBasisNoID">Other legal basis without an identifier</entry>
<entry key="group|name|GR-Procedure-MainLegalBasis">Правно основание</entry>
<entry key="group|name|GR-Procedure-MaxLots">Максимален брой лотове</entry>
<entry key="group|name|GR-Procedure-PinTerminated">Край на ПИН</entry>
<entry key="group|name|GR-Procedure-PlaceOfPerformance">Place of performance</entry>
<entry key="group|name|GR-Procedure-Procedure">Възлагане на поръчката</entry>
<entry key="group|name|GR-Procedure-Procedure-subsection">Възлагане на поръчката</entry>
<entry key="group|name|GR-Procedure-Purpose">Цел;</entry>
<entry key="group|name|GR-Procedure-Scope">Обхват на поръчката</entry>
<entry key="group|name|GR-Procedure-Scope-MainClassification">Класиране</entry>
<entry key="group|name|GR-Procedure-TenderingTerms">Тръжни условия</entry>
<entry key="group|name|GR-Recurrence">Информация за повторяемост</entry>
<entry key="group|name|GR-ReservedParticipation">Reserved procurement</entry>
<entry key="group|name|GR-Result">Резултат</entry>
<entry key="group|name|GR-SettledContract-1">Поръчка 1</entry>
<entry key="group|name|GR-SettledContract-2">Поръчка 2</entry>
<entry key="group|name|GR-SettledContract-3">Поръчка 3</entry>
<entry key="group|name|GR-SettledContract-Section">Договори, поръчки</entry>
<entry key="group|name|GR-Tender">Търг</entry>
<entry key="group|name|GR-TenderingParty-Section">Участници в търга</entry>
<entry key="group|name|GR-TouchPoint-Address">Адрес на отдела (ако е различен от основния)</entry>
<entry key="group|name|GR-TouchPoint-Contact">Звено за контакт на отдела (ако е различно от основното)</entry>
<entry key="group|name|GR-UBO-Subsection">Действителен собственик</entry>
<entry key="group|name|GR-UBO-Winner">Националност на собственика на победителя</entry>
<entry key="group|name|GR-Unpublish-BT-09">Трансгранично право (публикувано по-късно)</entry>
<entry key="group|name|GR-Unpublish-BT-105">Вид на процедурата (публикувана по-късно)</entry>
<entry key="group|name|GR-Unpublish-BT-105-Procedure">Type of procedure (published later)</entry>
<entry key="group|name|GR-Unpublish-BT-106">Ускорена процедура (публикувана по-късно)</entry>
<entry key="group|name|GR-Unpublish-BT-1118">Прогнозна стойност на рамковото споразумение (публикувано по-късно)</entry>
<entry key="group|name|GR-Unpublish-BT-118">Прогнозна стойност на рамковото споразумение (публикувано по-късно)</entry>
<entry key="group|name|GR-Unpublish-BT-1252">Идентификационен номер на предишната процедура, обосноваваща прякото възлагане (публикуван по-късно)</entry>
<entry key="group|name|GR-Unpublish-BT-1252-Procedure">ID of the previous procedure justifying direct award (published later)</entry>
<entry key="group|name|GR-Unpublish-BT-135">Описание на прякото възлагане (публикувано по-късно)</entry>
<entry key="group|name|GR-Unpublish-BT-135-Procedure">Description of direct award (published later)</entry>
<entry key="group|name|GR-Unpublish-BT-1351">Обосновка за ускорената процедура (публикувана по-късно)</entry>
<entry key="group|name|GR-Unpublish-BT-136">Обосновка за прякото възлагане (публикувано по-късно)</entry>
<entry key="group|name|GR-Unpublish-BT-142">Статус на избор на победител (публикуван по-късно)</entry>
<entry key="group|name|GR-Unpublish-BT-142-LotResult">Winner selection status (published later)</entry>
<entry key="group|name|GR-Unpublish-BT-144">Причината, поради която победителят не е избран (публикуван по-късно)</entry>
<entry key="group|name|GR-Unpublish-BT-144-LotResult">The reason why a winner was not chosen (published later)</entry>
<entry key="group|name|GR-Unpublish-BT-156">Прогнозна стойност на рамковите споразумения в групата обособени позиции (публикувана по-късно)</entry>
<entry key="group|name|GR-Unpublish-BT-160">Прогнозни приходи от купувача, който е предоставил концесията (публикуван по-късно)</entry>
<entry key="group|name|GR-Unpublish-BT-161">Стойност на всички поръчки, възложени в рамките на тази процедура (публикувана по-късно)</entry>
<entry key="group|name|GR-Unpublish-BT-162">Прогнозни приходи от ползвателите на концесията (публикуван по-късно)</entry>
<entry key="group|name|GR-Unpublish-BT-163">Метод, използван за изчисляване на прогнозната стойност на концесията (публикуван по-късно)</entry>
<entry key="group|name|GR-Unpublish-BT-171">Класирайте се в списъка на победителите (публикуван по-късно)</entry>
<entry key="group|name|GR-Unpublish-BT-191">Държава на произход на продукта или услугата (публикувана по-късно)</entry>
<entry key="group|name|GR-Unpublish-BT-193">Офертата е вариант (публикуван по-късно)</entry>
<entry key="group|name|GR-Unpublish-BT-539">Вид (публикуван по-късно)</entry>
<entry key="group|name|GR-Unpublish-BT-539-Lot">Type (published later)</entry>
<entry key="group|name|GR-Unpublish-BT-539-LotsGroup">Вид (публикуван по-късно)</entry>
<entry key="group|name|GR-Unpublish-BT-540">Описание (публикувано по-късно)</entry>
<entry key="group|name|GR-Unpublish-BT-540-Lot">Description (published later)</entry>
<entry key="group|name|GR-Unpublish-BT-540-LotsGroup">Описание (публикувано по-късно)</entry>
<entry key="group|name|GR-Unpublish-BT-541">Номер на критерия за възлагане (публикуван по-късно)</entry>
<entry key="group|name|GR-Unpublish-BT-541-Lot">Award criterion number (published later)</entry>
<entry key="group|name|GR-Unpublish-BT-541-LotsGroup">Номер на критерия за възлагане (публикуван по-късно)</entry>
<entry key="group|name|GR-Unpublish-BT-5421">Номерът е вид тегло (публикувано по-късно)</entry>
<entry key="group|name|GR-Unpublish-BT-5421-Lot">Number is a type of weight (published later)</entry>
<entry key="group|name|GR-Unpublish-BT-5421-LotsGroup">Номерът е вид тегло (публикувано по-късно)</entry>
<entry key="group|name|GR-Unpublish-BT-5422">Номерът е фиксирана стойност (публикувана по-късно)</entry>
<entry key="group|name|GR-Unpublish-BT-5422-Lot">Number is a fixed value (published later)</entry>
<entry key="group|name|GR-Unpublish-BT-5422-LotsGroup">Номерът е фиксирана стойност (публикувана по-късно)</entry>
<entry key="group|name|GR-Unpublish-BT-5423">Номерът е вид праг (публикуван по-късно)</entry>
<entry key="group|name|GR-Unpublish-BT-5423-Lot">Number is a type of threshold (published later)</entry>
<entry key="group|name|GR-Unpublish-BT-5423-LotsGroup">Номерът е вид праг (публикуван по-късно)</entry>
<entry key="group|name|GR-Unpublish-BT-543">Описание на метода, който трябва да се използва, ако претеглянето не може да бъде изразено чрез критерии (публикувано по-късно)</entry>
<entry key="group|name|GR-Unpublish-BT-543-Lot">Description of the method to be used if weighting cannot be expressed by criteria (published later)</entry>
<entry key="group|name|GR-Unpublish-BT-543-LotsGroup">Описание на метода, който трябва да се използва, ако претеглянето не може да бъде изразено чрез критерии (публикувано по-късно)</entry>
<entry key="group|name|GR-Unpublish-BT-553">Стойност на възлагането на подизпълнители (публикувано по-късно)</entry>
<entry key="group|name|GR-Unpublish-BT-554">Описание (публикувано по-късно)</entry>
<entry key="group|name|GR-Unpublish-BT-555">Процент на подизпълнителите (публикуван по-късно)</entry>
<entry key="group|name|GR-Unpublish-BT-556">Идентификационен код на обособена позиция за групова рамкова стойност (публикуван по-късно)</entry>
<entry key="group|name|GR-Unpublish-BT-709">Максимална стойност на рамковото споразумение (публикувано по-късно)</entry>
<entry key="group|name|GR-Unpublish-BT-710">Стойност на най-ниската допустима оферта (публикувана по-късно)</entry>
<entry key="group|name|GR-Unpublish-BT-711">Стойност на най-високата допустима оферта (публикувана по-късно)</entry>
<entry key="group|name|GR-Unpublish-BT-712">Брой на жалбоподателите (публикуван по-късно)</entry>
<entry key="group|name|GR-Unpublish-BT-720">Стойност на резултата (публикувана по-късно)</entry>
<entry key="group|name|GR-Unpublish-BT-720-Tender">Стойност на резултата (публикувана по-късно)</entry>
<entry key="group|name|GR-Unpublish-BT-730">Прогнозна стойност на частта от договора, която изпълнителят ще възложи на трети страни за подизпълнение (публикувана по-късно)</entry>
<entry key="group|name|GR-Unpublish-BT-731">Прогнозен процент на поръчката, която изпълнителят ще възложи на трети страни, в сравнение с целия договор (публикуван по-късно)</entry>
<entry key="group|name|GR-Unpublish-BT-733">Обосновка за непосочване на тежестта на критериите за възлагане (публикувана по-късно)</entry>
<entry key="group|name|GR-Unpublish-BT-733-Lot">Обосновка за непосочване на тежестта на критериите за възлагане (публикувана по-късно)</entry>
<entry key="group|name|GR-Unpublish-BT-733-LotsGroup">Обосновка за непосочване на тежестта на критериите за възлагане (публикувана по-късно)</entry>
<entry key="group|name|GR-Unpublish-BT-734">Име (публикувано по-късно)</entry>
<entry key="group|name|GR-Unpublish-BT-734-Lot">Name (published later)</entry>
<entry key="group|name|GR-Unpublish-BT-734-LotsGroup">Име (публикувано по-късно)</entry>
<entry key="group|name|GR-Unpublish-BT-759">Брой получени оферти или заявления за участие (публикувани по-късно)</entry>
<entry key="group|name|GR-Unpublish-BT-760">Вид на получените коментари (публикувани по-късно)</entry>
<entry key="group|name|GR-Unpublish-BT-773">Възлагане на подизпълнители (публикувано по-късно)</entry>
<entry key="group|name|GR-Unpublish-BT-88">Описание на процедурата (публикувано по-късно)</entry>
<entry key="group|name|GR-Unpublish-BT-88-Procedure">Description of the procedure (published later)</entry>
<entry key="group|name|GR-Winner">Победител</entry>
<entry key="group|name|ND-BuyerReviewComplainants">Requests to review decisions</entry>
<entry key="group|name|ND-Change">Information about the change</entry>
<entry key="group|name|ND-ContractEUFunds">EU funds used in the contract</entry>
<entry key="group|name|ND-ContractModification">Information about the modification</entry>
<entry key="group|name|ND-ContractingParty">Buyer</entry>
<entry key="group|name|ND-CrossBorderLaw">Cross-border law</entry>
<entry key="group|name|ND-ExclusionGrounds">Exclusion grounds</entry>
<entry key="group|name|ND-LocalLegalBasisWithID">Other legal basis with an identifier</entry>
<entry key="group|name|ND-Lot">Information about the lot</entry>
<entry key="group|name|ND-LotAdditionalClassification">Additional classification</entry>
<entry key="group|name|ND-LotAwardCriteria">Award criteria</entry>
<entry key="group|name|ND-LotAwardCriterion">Award criterion</entry>
<entry key="group|name|ND-LotAwardCriterionParameter">Award criterion</entry>
<entry key="group|name|ND-LotAwardCriterionParameters">Award criteria</entry>
<entry key="group|name|ND-LotPlacePerformance">Place of performance</entry>
<entry key="group|name|ND-LotPreviousPlanning">Reference to previous planning</entry>
<entry key="group|name|ND-LotResult">Result of the lot</entry>
<entry key="group|name|ND-LotTender">Submitted tender</entry>
<entry key="group|name|ND-LotsGroup">Information about groups of lots</entry>
<entry key="group|name|ND-LotsGroupAwardCriteria">Award criteria</entry>
<entry key="group|name|ND-LotsGroupAwardCriterion">Award criteria</entry>
<entry key="group|name|ND-Modification">Contract modification</entry>
<entry key="group|name|ND-ModificationReason">Reason for contract modification</entry>
<entry key="group|name|ND-NoticeResultGroupFA">Maximum value of group of lots</entry>
<entry key="group|name|ND-Organization">Organisations mentioned in the notice</entry>
<entry key="group|name|ND-Part">Information about the part</entry>
<entry key="group|name|ND-PartAdditionalClassification">Additional classification</entry>
<entry key="group|name|ND-PartPlacePerformance">Place of performance</entry>
<entry key="group|name|ND-PartPreviousPlanning">Previous planning reference</entry>
<entry key="group|name|ND-Prize">Information about prizes</entry>
<entry key="group|name|ND-ProcedureAdditionalCommodityClassification">Additional classification</entry>
<entry key="group|name|ND-ProcedurePlacePerformanceAdditionalInformation">Additional information about place of performance</entry>
<entry key="group|name|ND-RewardsPenalties">Information on rewards and penalties</entry>
<entry key="group|name|ND-SelectionCriteria">Selection criteria</entry>
<entry key="group|name|ND-ServiceProviderParty">Service provider</entry>
<entry key="group|name|ND-SettledContract">Settled contract</entry>
<entry key="group|name|ND-Tenderer">Tendering parties</entry>
<entry key="group|name|ND-TenderingParty">Tendering party</entry>
<entry key="group|name|ND-Touchpoint">Specific contact points</entry>
<entry key="group|name|ND-UBO">Beneficial owner</entry>
<entry key="group|name|Root">The root node</entry>
</properties>
